atomicswap/__init__.py
atomicswap/__main__.py
atomicswap/bonds/__init__.py
atomicswap/btc/__init__.py
atomicswap/btc/cli/__init__.py
atomicswap/btc/cli/btc_script_cli.py
atomicswap/btc/gui/__init__.py
atomicswap/btc/gui/btc_script.py
atomicswap/contrib/__init__.py
atomicswap/contrib/images/__init__.py
atomicswap/contrib/images/btc.png
atomicswap/contrib/images/config.png
atomicswap/contrib/images/ltc.png
atomicswap/contrib/images/swap0.png
atomicswap/contrib/images/swap1.png
atomicswap/contrib/images/swap10.png
atomicswap/contrib/images/swap11.png
atomicswap/contrib/images/swap12.png
atomicswap/contrib/images/swap13.png
atomicswap/contrib/images/swap14.png
atomicswap/contrib/images/swap15.png
atomicswap/contrib/images/swap16.png
atomicswap/contrib/images/swap17.png
atomicswap/contrib/images/swap18.png
atomicswap/contrib/images/swap19.png
atomicswap/contrib/images/swap2.png
atomicswap/contrib/images/swap20.png
atomicswap/contrib/images/swap21.png
atomicswap/contrib/images/swap22.png
atomicswap/contrib/images/swap23.png
atomicswap/contrib/images/swap24.png
atomicswap/contrib/images/swap3.png
atomicswap/contrib/images/swap4.png
atomicswap/contrib/images/swap5.png
atomicswap/contrib/images/swap6.png
atomicswap/contrib/images/swap7.png
atomicswap/contrib/images/swap8.png
atomicswap/contrib/images/swap9.png
atomicswap/contrib/images/tg_offline.png
atomicswap/depends/__init__.py
atomicswap/depends/config.py
atomicswap/depends/spinner.py
atomicswap/depends/utils.py
atomicswap/ltc/__init__.py
atomicswap/ltc/cli/__init__.py
atomicswap/ltc/cli/ltc_script_cli.py
atomicswap/ltc/gui/__init__.py
atomicswap/ltc/gui/ltc_script.py
atomicswap/user_swaps/__init__.py
atomicswap/wallets/__init__.py
TannhauserGate-0.3.2.dev0.dist-info/LICENSE
TannhauserGate-0.3.2.dev0.dist-info/METADATA
TannhauserGate-0.3.2.dev0.dist-info/WHEEL
TannhauserGate-0.3.2.dev0.dist-info/entry_points.txt
TannhauserGate-0.3.2.dev0.dist-info/top_level.txt
TannhauserGate-0.3.2.dev0.dist-info/RECORD
