Metadata-Version: 2.1
Name: TannhauserGate
Version: 0.3.2.dev0
Summary: P2P Cross Chain Atomic Swap
Home-page: https://github.com/TannhauserGate420/tannhauser
Author: iizegrim
Author-email: iizegrim@protonmail.com
Keywords: tannhausergate,tannhauser,atomicswap,atomic,swap,bitcoin,litecoin,cryptocurrencies
Classifier: Development Status :: 3 - Alpha
Classifier: Environment :: X11 Applications :: Qt
Classifier: Intended Audience :: End Users/Desktop
Classifier: License :: OSI Approved :: GNU General Public License v3 (GPLv3)
Classifier: Operating System :: MacOS
Classifier: Operating System :: Microsoft :: Windows
Classifier: Operating System :: POSIX
Classifier: Programming Language :: Python :: 3 :: Only
Classifier: Topic :: Utilities
Requires-Python: >=3.7, <4
License-File: LICENSE
Requires-Dist: python-bitcoinrpc
Requires-Dist: python-bitcoinlib
Requires-Dist: python-litecoinlib
Requires-Dist: requests
Requires-Dist: emoji
Requires-Dist: PyQt5
Requires-Dist: stem
Requires-Dist: fake-http-header
Requires-Dist: PySocks
Requires-Dist: cryptography
